tui_audioplayer/Playlists/Jazz/101SMOOTHJAZZ.png
tui_audioplayer/Playlists/Jazz/95_5SmoothJazz.png
tui_audioplayer/Playlists/Jazz/AardvarkBluesFM.png
tui_audioplayer/Playlists/Jazz/AmazingSmoothandJazz.png
tui_audioplayer/Playlists/Jazz/BigBlueSwing.png
tui_audioplayer/Playlists/Jazz/BluesMusicFan.png
tui_audioplayer/Playlists/Jazz/ChiaroscuroFineJazzRecordings.png
tui_audioplayer/Playlists/Jazz/CoolJazzFlorida.png
tui_audioplayer/Playlists/Jazz/CroonerRadio.png
tui_audioplayer/Playlists/Jazz/DeepPocketsJazz.png
tui_audioplayer/Playlists/Jazz/GotRadioBigBandLand.png
tui_audioplayer/Playlists/Jazz/GotRadioBitOBlues.png
tui_audioplayer/Playlists/Jazz/GotRadioJazzSoSmooth.png
tui_audioplayer/Playlists/Jazz/Jazz88.3FM.png
tui_audioplayer/Playlists/Jazz/Jazz90.1.png
tui_audioplayer/Playlists/Jazz/JazzBitesRadio.com.png
tui_audioplayer/Playlists/Jazz/JazzOnFirst[RadioAvenue.com].png
"tui_audioplayer/Playlists/Jazz/KDKIAdultStandards,Jazz,BigBand.png"
tui_audioplayer/Playlists/Jazz/KJazz.png
tui_audioplayer/Playlists/Jazz/KMHDJazzRadio.png
tui_audioplayer/Playlists/Jazz/KTSUTexasSouthernUniversity.png
tui_audioplayer/Playlists/Jazz/KUNVUniversityofNevada.png
tui_audioplayer/Playlists/Jazz/McQsJazz.com.png
tui_audioplayer/Playlists/Jazz/PureJazzRadio.png
tui_audioplayer/Playlists/Jazz/RadioDismuke.png
tui_audioplayer/Playlists/Jazz/Reggae141.png
tui_audioplayer/Playlists/Jazz/Sax4Ever.png
tui_audioplayer/Playlists/Jazz/SmoothJazzFlorida.png
tui_audioplayer/Playlists/Jazz/SmoothJazzMixNewYork.png
tui_audioplayer/Playlists/Jazz/SmoothJazzSouthFlorida.png
tui_audioplayer/Playlists/Jazz/SonicUniverse.png
tui_audioplayer/Playlists/Jazz/SwingCityRadio.png
tui_audioplayer/Playlists/Jazz/SwingStreetRadio.png
tui_audioplayer/Playlists/Jazz/TheJazzGroove.png
tui_audioplayer/Playlists/Jazz/ThePenthouse.png
tui_audioplayer/Playlists/Jazz/ThePittsburghJazzChannel.png
tui_audioplayer/Playlists/Jazz/TheSound.png
tui_audioplayer/Playlists/Jazz/WNOZSmoothJazz.png
tui_audioplayer-0.1.7.dist-info/WHEEL
tui_audioplayer-0.1.7.dist-info/entry_points.txt
tui_audioplayer-0.1.7.dist-info/METADATA
tui_audioplayer-0.1.7.dist-info/RECORD
