Metadata-Version: 2.3
Name: tui-audioplayer
Version: 0.1.7
Summary: TUI WebRadio player
Keywords: textual,cli,WebRadio,command line,console
Author: Alfredo Cubitos
Requires-Dist: textual>=6.11.0
Requires-Dist: python-vlc>=3.0
Requires-Dist: textual-image>=0.8
Requires-Python: >=3.13
Project-URL: Homepage, https://github.com/AlfredoCubitos/tui_audioplayer
